setup.py
prob_distributions_pkg/Binomialdistribution.py
prob_distributions_pkg/Gaussiandistribution.py
prob_distributions_pkg/Generaldistribution.py
prob_distributions_pkg/__init__.py
prob_distributions_pkg.egg-info/PKG-INFO
prob_distributions_pkg.egg-info/SOURCES.txt
prob_distributions_pkg.egg-info/dependency_links.txt
prob_distributions_pkg.egg-info/not-zip-safe
prob_distributions_pkg.egg-info/top_level.txt