Metadata-Version: 1.0
Name: prob-distributions-pkg
Version: 0.1
Summary: Gaussian and Binomial distributions
Home-page: UNKNOWN
Author: Sahil Saxena
Author-email: sahil.passion@gmail.com
License: UNKNOWN
Platform: UNKNOWN
